schlange/__init__.py
schlange/cli.py
schlange/einfach.py
schlange/functions.py
schlange/import_hook.py
schlange/jupyter_magic.py
schlange/keywords.py
schlange/magic.py
schlange/smart_import.py
schlange/transformer.py
schlange-0.1.6.dist-info/licenses/LICENSE
schlange-0.1.6.dist-info/METADATA
schlange-0.1.6.dist-info/WHEEL
schlange-0.1.6.dist-info/entry_points.txt
schlange-0.1.6.dist-info/top_level.txt
schlange-0.1.6.dist-info/RECORD
