Metadata-Version: 2.4
Name: schlange
Version: 0.1.6
Summary: 🐍 Python auf Deutsch - Deutsche Schlüsselwörter und .schlange Dateien für Python
Home-page: https://github.com/yourusername/schlange
Author: Konja Rehm
Author-email: Konja Rehm <private@konja-rehm.de>
License: MIT
Project-URL: Homepage, https://github.com/Nokohokon/schlange
Project-URL: Bug Reports, https://github.com/Nokohokon/schlange/issues
Project-URL: Source, https://github.com/Nokohokon/schlange
Project-URL: Documentation, https://github.com/Nokohokon/schlange#readme
Keywords: deutsch,german,python,education,programming,localization,schlange,deutsche-syntax,python-deutsch,german-python,educational-tool,programming-language,syntax-transformation
Classifier: Development Status :: 4 - Beta
Classifier: Intended Audience :: Education
Classifier: Intended Audience :: Developers
Classifier: Natural Language :: German
Classifier: Operating System :: OS Independent
Classifier: Programming Language :: Python :: 3
Classifier: Programming Language :: Python :: 3.6
Classifier: Programming Language :: Python :: 3.7
Classifier: Programming Language :: Python :: 3.8
Classifier: Programming Language :: Python :: 3.9
Classifier: Programming Language :: Python :: 3.10
Classifier: Programming Language :: Python :: 3.11
Classifier: Programming Language :: Python :: 3.12
Classifier: Topic :: Education
Classifier: Topic :: Software Development :: Libraries :: Python Modules
Classifier: Topic :: Software Development :: Localization
Classifier: Topic :: Software Development :: Interpreters
Classifier: License :: OSI Approved :: MIT License
Requires-Python: >=3.6
License-File: LICENSE
Provides-Extra: jupyter
Requires-Dist: IPython>=7.0.0; extra == "jupyter"
Provides-Extra: dev
Requires-Dist: pytest>=6.0; extra == "dev"
Requires-Dist: black; extra == "dev"
Requires-Dist: flake8; extra == "dev"
Requires-Dist: twine; extra == "dev"
Requires-Dist: build; extra == "dev"
Dynamic: author
Dynamic: home-page
Dynamic: license-file
Dynamic: requires-python
